pymc_bart/__init__.py
pymc_bart/bart.py
pymc_bart/pgbart.py
pymc_bart/split_rules.py
pymc_bart/tree.py
pymc_bart/utils.py
pymc_bart-0.11.0.dist-info/licenses/LICENSE
pymc_bart-0.11.0.dist-info/METADATA
pymc_bart-0.11.0.dist-info/WHEEL
pymc_bart-0.11.0.dist-info/top_level.txt
pymc_bart-0.11.0.dist-info/RECORD
