Metadata-Version: 2.4
Name: pymc_bart
Version: 0.11.0
Summary: Bayesian Additive Regression Trees for Probabilistic programming with PyMC
Home-page: http://github.com/pymc-devs/pymc-bart
Maintainer: PyMC Developers
Maintainer-email: pymc.devs@gmail.com
License: Apache License, Version 2.0
Classifier: Development Status :: 5 - Production/Stable
Classifier: Programming Language :: Python
Classifier: Programming Language :: Python :: 3
Classifier: Programming Language :: Python :: 3.11
Classifier: Programming Language :: Python :: 3.12
Classifier: Programming Language :: Python :: 3.13
Classifier: License :: OSI Approved :: Apache Software License
Classifier: Intended Audience :: Science/Research
Classifier: Topic :: Scientific/Engineering
Classifier: Topic :: Scientific/Engineering :: Mathematics
Classifier: Operating System :: OS Independent
Requires-Python: >=3.8
License-File: LICENSE
Requires-Dist: pymc>=5.24.0
Requires-Dist: arviz-stats[xarray]>=0.6.0
Requires-Dist: numba
Requires-Dist: matplotlib
Requires-Dist: numpy>=2.0
Dynamic: classifier
Dynamic: description
Dynamic: description-content-type
Dynamic: home-page
Dynamic: license
Dynamic: license-file
Dynamic: maintainer
Dynamic: maintainer-email
Dynamic: requires-dist
Dynamic: requires-python
Dynamic: summary
